MANIFEST.in
README.md
README_pypi.md
requirements.txt
setup.py
hashmap_data_definitionOps.egg-info/PKG-INFO
hashmap_data_definitionOps.egg-info/SOURCES.txt
hashmap_data_definitionOps.egg-info/dependency_links.txt
hashmap_data_definitionOps.egg-info/entry_points.txt
hashmap_data_definitionOps.egg-info/requires.txt
hashmap_data_definitionOps.egg-info/top_level.txt
hm_datadefinitionops/__init__.py
hm_datadefinitionops/__main__.py
hm_datadefinitionops/appbase.py
hm_datadefinitionops/apply_phase.py
hm_datadefinitionops/delta_identifier.py
hm_datadefinitionops/merge_with_registry.py
hm_datadefinitionops/plan_phase.py
hm_datadefinitionops/script_generator.py
hm_datadefinitionops/snowconnection.py
hmddops_resources/__init__.py
hmddops_resources/config/__init__.py
hmddops_resources/config/config.yaml
hmddops_resources/config/metadata_query.yaml
hmddops_resources/templates/__init__.py
hmddops_resources/templates/generic.sql
hmddops_resources/templates/grants.sql
hmddops_resources/templates/plan_report.md
hmddops_resources/templates/schema.sql
hmddops_resources/templates/table.sql
tests/__init__.py
tests/conftest.py
tests/test_appbase.py
tests/test_delta_identifier.py
tests/test_dwmetareplicate_snowflake.py