Metadata-Version: 2.1
Name: hashmap-data-definitionOps
Version: 0.0.0.27
Summary: An alternative approach utility for data warehouse DevOps for Snowflake - limited usage.
Home-page: https://gitlab.com/hashmapinc/oss/dwmetareplicate_snowflake
Author: Hashmap, Inc
Author-email: accelerators@hashmapinc.com
License: UNKNOWN
Platform: UNKNOWN
Classifier: Development Status :: 4 - Beta
Classifier: Environment :: Console
Classifier: Programming Language :: Python :: 3
Classifier: License :: OSI Approved :: Apache Software License
Classifier: Intended Audience :: Developers
Classifier: Operating System :: OS Independent
Classifier: Programming Language :: Python :: Implementation
Classifier: Topic :: Database
Classifier: Topic :: Software Development :: Code Generators
Classifier: Topic :: Utilities
Requires-Python: >=3.6
